odoo10_addon_sale_stock_picking_blocking_sale_manual_delivery-10.0.1.0.1-py3.8-nspkg.pth
odoo/addons/sale_stock_picking_blocking_sale_manual_delivery/README.rst
odoo/addons/sale_stock_picking_blocking_sale_manual_delivery/__init__.py
odoo/addons/sale_stock_picking_blocking_sale_manual_delivery/__manifest__.py
odoo/addons/sale_stock_picking_blocking_sale_manual_delivery/i18n/sale_stock_picking_blocking_sale_manual_delivery.pot
odoo/addons/sale_stock_picking_blocking_sale_manual_delivery/models/__init__.py
odoo/addons/sale_stock_picking_blocking_sale_manual_delivery/models/sale_order_line.py
odoo/addons/sale_stock_picking_blocking_sale_manual_delivery/static/description/icon.png
odoo10_addon_sale_stock_picking_blocking_sale_manual_delivery-10.0.1.0.1.dist-info/METADATA
odoo10_addon_sale_stock_picking_blocking_sale_manual_delivery-10.0.1.0.1.dist-info/WHEEL
odoo10_addon_sale_stock_picking_blocking_sale_manual_delivery-10.0.1.0.1.dist-info/namespace_packages.txt
odoo10_addon_sale_stock_picking_blocking_sale_manual_delivery-10.0.1.0.1.dist-info/top_level.txt
odoo10_addon_sale_stock_picking_blocking_sale_manual_delivery-10.0.1.0.1.dist-info/RECORD
